checkpoint/checkpoint_pb2.py
checkpoint/checkpoint_pb2_grpc.py
examples/basic_checkpoint.py
omium/__init__.py
omium/agent.py
omium/chat.py
omium/checkpoint.py
omium/cli.py
omium/client.py
omium/config.py
omium/consensus.py
omium/consensus_client.py
omium/discovery.py
omium/output.py
omium/policy_client.py
omium/project.py
omium/remote_client.py
omium/streaming.py
omium/tracing_client.py
omium/websocket_client.py
omium/adapters/__init__.py
omium/adapters/base.py
omium/adapters/crewai_adapter.py
omium/adapters/crewai_yaml_adapter.py
omium/adapters/langgraph.py
omium/adapters/langgraph_adapter.py
omium/integrations/__init__.py
omium/integrations/callbacks.py
omium/integrations/core.py
omium/integrations/crewai.py
omium/integrations/decorators.py
omium/integrations/langgraph.py
omium/integrations/tracer.py
omium/proto/__init__.py
omium/proto/checkpoint/__init__.py
omium/proto/consensus/__init__.py
omium/proto/policy/__init__.py
omium/proto/tracing/__init__.py
omium/tui/__init__.py
omium/tui/app.py
omium-0.3.2.dist-info/licenses/LICENSE.md
scripts/generate_consensus_proto.py
omium-0.3.2.dist-info/METADATA
omium-0.3.2.dist-info/WHEEL
omium-0.3.2.dist-info/entry_points.txt
omium-0.3.2.dist-info/top_level.txt
omium-0.3.2.dist-info/RECORD
