Metadata-Version: 2.4
Name: omium
Version: 0.3.2
Summary: Omium SDK for Python - Fault-tolerant agent operating system
Author-email: Omium Team <anurag@omium.ai>
License: Proprietary
Keywords: agents,checkpointing,fault-tolerant,omium,multi-agent,AI
Classifier: Development Status :: 4 - Beta
Classifier: Intended Audience :: Developers
Classifier: Topic :: Software Development :: Libraries :: Python Modules
Classifier: Programming Language :: Python :: 3
Classifier: Programming Language :: Python :: 3.9
Classifier: Programming Language :: Python :: 3.10
Classifier: Programming Language :: Python :: 3.11
Classifier: Programming Language :: Python :: 3.12
Requires-Python: >=3.9
License-File: LICENSE.md
Requires-Dist: grpcio<2.0,>=1.69.0
Requires-Dist: grpcio-tools<1.71.0,>=1.69.0
Requires-Dist: protobuf<6.0,>=5.26.1
Requires-Dist: pydantic>=2.5.0
Requires-Dist: httpx>=0.25.0
Requires-Dist: click>=8.1.0
Requires-Dist: websockets>=12.0
Requires-Dist: rich>=13.7.0
Requires-Dist: typer>=0.9.0
Requires-Dist: alive-progress>=3.1.0
Requires-Dist: textual>=0.47.0
Requires-Dist: tomli>=2.0.0; python_version < "3.11"
Provides-Extra: dev
Requires-Dist: pytest>=7.4.0; extra == "dev"
Requires-Dist: pytest-asyncio>=0.21.0; extra == "dev"
Requires-Dist: black>=23.0.0; extra == "dev"
Requires-Dist: isort>=5.12.0; extra == "dev"
Requires-Dist: mypy>=1.7.0; extra == "dev"
Requires-Dist: build>=1.0.0; extra == "dev"
Requires-Dist: twine>=4.0.2; extra == "dev"
Dynamic: license-file
